[
    {
        "school":"National Institute of Technology Karnataka",
        "degree":"Bachelor of Technology",
        "major":"Electronics and Communication",
        "range":"2003 - 2007"
    },
    {
        "school":"Kendriya Vidyalaya, Dimapur",
        "degree":"All India Senior School Certificate Examination",
        "major":"Science",
        "range":"2001 - 2003"
    },
    {
        "school":"Kendriya Vidyalaya, Bokajan",
        "degree":"All India Secondary School Examination",
        "range":"1999 - 2001"
    }
]
